chatwithyourcode/__init__.py
chatwithyourcode-0.0.0.dist-info/METADATA
chatwithyourcode-0.0.0.dist-info/WHEEL
chatwithyourcode-0.0.0.dist-info/top_level.txt
chatwithyourcode-0.0.0.dist-info/RECORD
