Metadata-Version: 2.1
Name: chatwithyourcode
Version: 0.0.0
Summary: Coming soon
Author-email: Shane Barratt <shane@chatwithyourcode.com>
